odoo/addons/ssi_commission/README.rst
odoo/addons/ssi_commission/__init__.py
odoo/addons/ssi_commission/__manifest__.py
odoo/addons/ssi_commission/menu.xml
odoo/addons/ssi_commission/data/approval_template_data.xml
odoo/addons/ssi_commission/data/base_automation_data.xml
odoo/addons/ssi_commission/data/ir_actions_server_data.xml
odoo/addons/ssi_commission/data/ir_sequence_data.xml
odoo/addons/ssi_commission/data/policy_template_data.xml
odoo/addons/ssi_commission/data/sequence_template_data.xml
odoo/addons/ssi_commission/models/__init__.py
odoo/addons/ssi_commission/models/commission.py
odoo/addons/ssi_commission/models/commission_detail.py
odoo/addons/ssi_commission/models/commission_item.py
odoo/addons/ssi_commission/models/commission_item_computation.py
odoo/addons/ssi_commission/models/commission_tax.py
odoo/addons/ssi_commission/models/commission_type.py
odoo/addons/ssi_commission/models/commission_type_item.py
odoo/addons/ssi_commission/models/marketing_commission.py
odoo/addons/ssi_commission/models/marketing_commission_detail.py
odoo/addons/ssi_commission/models/marketing_commission_item.py
odoo/addons/ssi_commission/models/marketing_commission_item_computation.py
odoo/addons/ssi_commission/models/marketing_commission_tax.py
odoo/addons/ssi_commission/models/marketing_commission_type.py
odoo/addons/ssi_commission/models/marketing_commission_type_item.py
odoo/addons/ssi_commission/security/ir.model.access.csv
odoo/addons/ssi_commission/security/ir_module_category_data.xml
odoo/addons/ssi_commission/security/ir_rule_data.xml
odoo/addons/ssi_commission/security/res_group_data.xml
odoo/addons/ssi_commission/static/description/icon.png
odoo/addons/ssi_commission/templates/mixin_risk_analysis_templates.xml
odoo/addons/ssi_commission/views/commission_item_views.xml
odoo/addons/ssi_commission/views/commission_type_views.xml
odoo/addons/ssi_commission/views/commission_views.xml
odoo/addons/ssi_commission/views/marketing_commission_item_views.xml
odoo14_addon_ssi_commission-14.0.1.5.0.dist-info/METADATA
odoo14_addon_ssi_commission-14.0.1.5.0.dist-info/WHEEL
odoo14_addon_ssi_commission-14.0.1.5.0.dist-info/top_level.txt
odoo14_addon_ssi_commission-14.0.1.5.0.dist-info/RECORD
